facetorch/__init__.py
facetorch/base.py
facetorch/datastruct.py
facetorch/downloader.py
facetorch/logger.py
facetorch/transforms.py
facetorch/utils.py
facetorch/analyzer/__init__.py
facetorch/analyzer/core.py
facetorch/analyzer/detector/__init__.py
facetorch/analyzer/detector/core.py
facetorch/analyzer/detector/post.py
facetorch/analyzer/detector/pre.py
facetorch/analyzer/predictor/__init__.py
facetorch/analyzer/predictor/core.py
facetorch/analyzer/predictor/post.py
facetorch/analyzer/predictor/pre.py
facetorch/analyzer/reader/__init__.py
facetorch/analyzer/reader/core.py
facetorch/analyzer/unifier/__init__.py
facetorch/analyzer/unifier/core.py
facetorch/analyzer/utilizer/__init__.py
facetorch/analyzer/utilizer/align.py
facetorch/analyzer/utilizer/draw.py
facetorch/analyzer/utilizer/save.py
facetorch-0.6.0.dist-info/licenses/LICENSE
facetorch-0.6.0.dist-info/METADATA
facetorch-0.6.0.dist-info/WHEEL
facetorch-0.6.0.dist-info/top_level.txt
facetorch-0.6.0.dist-info/RECORD
