Metadata-Version: 2.4
Name: facetorch
Version: 0.6.0
Summary: Face analysis PyTorch framework.
Home-page: https://github.com/tomas-gajarsky/facetorch
Download-URL: https://pypi.org/project/facetorch/
Author: Tomas Gajarsky
Author-email: gajarsky.tomas@gmail.com
Maintainer: Tomas Gajarsky
Maintainer-email: gajarsky.tomas@gmail.com
Classifier: Development Status :: 3 - Alpha
Classifier: Environment :: Console
Classifier: Intended Audience :: Science/Research
Classifier: Intended Audience :: End Users/Desktop
Classifier: License :: OSI Approved :: Apache Software License
Classifier: Natural Language :: English
Classifier: Operating System :: OS Independent
Classifier: Programming Language :: Python :: 3
Classifier: Programming Language :: Python :: 3.8
Classifier: Programming Language :: Python :: 3.9
Classifier: Programming Language :: Python :: 3.10
Classifier: Programming Language :: Python :: 3.11
Classifier: Programming Language :: Python :: 3.12
Classifier: Topic :: Scientific/Engineering :: Artificial Intelligence
Classifier: Topic :: Software Development :: Libraries :: Python Modules
Requires-Python: >=3.8
License-File: LICENSE
Requires-Dist: codetiming>=1.2.0
Requires-Dist: googleapis-common-protos>=1.56.3
Requires-Dist: gdown>=3.11.0
Requires-Dist: hydra-core>=1.0.0
Requires-Dist: numpy>=1.18.2
Requires-Dist: pip>=20.0.2
Requires-Dist: python-json-logger>=2.0.0
Requires-Dist: torch<2.4,>=1.9.0
Requires-Dist: torchvision>=0.10.0
Requires-Dist: huggingface_hub>=0.16.0
Dynamic: author
Dynamic: author-email
Dynamic: classifier
Dynamic: description
Dynamic: description-content-type
Dynamic: download-url
Dynamic: home-page
Dynamic: license-file
Dynamic: maintainer
Dynamic: maintainer-email
Dynamic: requires-dist
Dynamic: requires-python
Dynamic: summary
